{
  "version": "nightly",
  "description": "Cross-platform tiling window manager",
  "homepage": "https://github.com/l0ngvh/Dome",
  "license": "MIT",
  "architecture": {
    "64bit": {
      "url": "https://github.com/l0ngvh/Dome/releases/download/v0.1.0/dome-0.1.0-x86_64-pc-windows-msvc.zip",
      "hash": "940320a88f8a43ac8ef2372e52b5941db65c5a04f4b1b3c44df6539d2d5d9ddc"
    }
  },
  "bin": "dome.exe",
  "checkver": "github",
  "autoupdate": {
    "architecture": {
      "64bit": {
        "url": "https://github.com/l0ngvh/Dome/releases/download/v$version/dome-$version-x86_64-pc-windows-msvc.zip"
      }
    }
  }
}
